{
  "name": "devcontainer",
  "dockerComposeFile": "docker-compose.yml",
  "service": "dev",
  "workspaceFolder": "/workspace",
  "shutdownAction": "stopCompose",
  "remoteUser": "ubuntu",
  "mounts": [
    "source=${localEnv:SSH_AUTH_SOCK},target=/ssh-agent,type=bind",
    "source=${localEnv:HOME}/.ssh/known_hosts,target=/home/ubuntu/.ssh/known_hosts,type=bind,readonly"
  ],
  "containerEnv": {
    "SSH_AUTH_SOCK": "/ssh-agent"
  },
  "customizations": {
    "vscode": {
      "extensions": [
        "ms-azuretools.vscode-docker",
        "dbaeumer.vscode-eslint",
        "esbenp.prettier-vscode"
      ]
    }
  }
}
